Metadata-Version: 2.1
Name: vitcifar10
Version: 0.0.5
Summary: Python module to train and test on CIFAR-10.
Home-page: https://github.com/luiscarlosgph/vitcifar10
Author: Luis C. Garcia-Peraza Herrera
Author-email: luiscarlos.gph@gmail.com
License: MIT License
Platform: UNKNOWN
License-File: LICENSE
